setup.py
anjana_distributions/Binomialdistribution.py
anjana_distributions/Gaussiandistribution.py
anjana_distributions/Generaldistribution.py
anjana_distributions/__init__.py
anjana_distributions.egg-info/PKG-INFO
anjana_distributions.egg-info/SOURCES.txt
anjana_distributions.egg-info/dependency_links.txt
anjana_distributions.egg-info/not-zip-safe
anjana_distributions.egg-info/top_level.txt